{"price": "\u00a3\u00a3\u00a3", "coordinates": {"longitude": -0.101486, "latitude": 51.520481}, "image_url": "https://s3-media1.fl.yelpcdn.com/bphoto/SKH7QWCTCNkeVdb8zYa73Q/o.jpg", "id": "st-john-bar-and-restaurant-london", "is_claimed": true, "name": "St John Bar and Restaurant", "rating": 4.5, "photos": ["https://s3-media1.fl.yelpcdn.com/bphoto/SKH7QWCTCNkeVdb8zYa73Q/o.jpg", "https://s3-media2.fl.yelpcdn.com/bphoto/sHiB_TDd3CV7Ezf-NnnmlQ/o.jpg", "https://s3-media2.fl.yelpcdn.com/bphoto/EbZVTiJYOvjZVKG56WZLFQ/o.jpg"], "is_closed": false, "phone": "+442072510848", "term": "restaurants", "review_count": 245, "location": {"address1": "26 St John Street", "address2": "", "zip_code": "EC1M 4AY", "country": "GB", "state": "XGL", "city": "London", "address3": ""}, "hours": [{"open": [{"day": 0, "is_overnight": false, "end": "1700", "start": "1200"}, {"day": 0, "is_overnight": false, "end": "0000", "start": "1800"}, {"day": 1, "is_overnight": false, "end": "1700", "start": "1200"}, {"day": 1, "is_overnight": false, "end": "0000", "start": "1800"}, {"day": 2, "is_overnight": false, "end": "1700", "start": "1200"}, {"day": 2, "is_overnight": false, "end": "0000", "start": "1800"}, {"day": 3, "is_overnight": false, "end": "1700", "start": "1200"}, {"day": 3, "is_overnight": false, "end": "0000", "start": "1800"}, {"day": 4, "is_overnight": false, "end": "1700", "start": "1200"}, {"day": 4, "is_overnight": false, "end": "0000", "start": "1800"}, {"day": 5, "is_overnight": false, "end": "0000", "start": "1800"}, {"day": 6, "is_overnight": false, "end": "1600", "start": "1230"}], "is_open_now": false, "hours_type": "REGULAR"}], "categories": [{"title": "British", "alias": "british"}, {"title": "Bars", "alias": "bars"}], "url": "https://www.yelp.com/biz/st-john-bar-and-restaurant-london?adjust_creative=92p07_JjKyriZTQxAXRiKQ&utm_campaign=yelp_api_v3&utm_medium=api_v3_business_lookup&utm_source=92p07_JjKyriZTQxAXRiKQ"}