{"news_desk": "Sports", "print_page": "7", "section_name": "Sports", "subsection_name": "Soccer", "byline": {"original": "By THE ASSOCIATED PRESS", "person": [], "organization": "THE ASSOCIATED PRESS"}, "abstract": null, "type_of_material": "Brief", "word_count": "102", "lead_paragraph": "Edinson Cavani scored a hat trick, and Zlatan Ibrahimovic scored twice as Paris St.-Germain thrashed Guingamp to take a step toward a third straight French title.", "pub_date": "2015-05-09T00:00:00Z", "document_type": "article", "slideshow_credits": null, "headline": {"main": "Paris St.-Germain\u00a0Closes In on Title With Rout of Guingamp", "content_kicker": "Sports Briefing | Soccer", "print_headline": "P.S.G. Closes In on Title"}, "snippet": "Edinson Cavani scored a hat trick, and Zlatan Ibrahimovic scored twice as Paris St.-Germain thrashed Guingamp to take a step toward a third straight French title.", "multimedia": [], "web_url": "http://www.nytimes.com/2015/05/09/sports/soccer/paris-st-germaincloses-in-on-title-with-rout-of-guingamp.html", "keywords": [{"rank": "1", "is_major": "N", "value": "Soccer", "name": "subject"}, {"rank": "2", "is_major": "N", "value": "UEFA Champions League (Soccer)", "name": "subject"}, {"rank": "3", "is_major": "N", "value": "Paris St-Germain FC (Soccer Team)", "name": "organizations"}, {"rank": "4", "is_major": "N", "value": "Cavani, Edinson", "name": "persons"}, {"rank": "5", "is_major": "N", "value": "Ibrahimovic, Zlatan", "name": "persons"}], "blog": [], "_id": "554d8d9638f0d8188877cd61", "source": "The New York Times"}