{"news_desk": "Business", "print_page": "2", "section_name": "Business Day", "subsection_name": null, "document_type": "article", "multimedia": [], "abstract": "AutoNation, largest dealership chain in the United States, reports 12 percent sales increase in December 2014 following outstanding report from auto industry.", "type_of_material": "Brief", "word_count": "76", "lead_paragraph": "The company, based in Fort Lauderdale, Fla., said on Tuesday that it sold 33,069 new vehicles in December.", "pub_date": "2015-01-07T00:00:00Z", "_id": "54ac7c5e38f0d8699a4c5d4b", "byline": {"contributor": "", "original": "By THE ASSOCIATED PRESS", "person": [], "organization": "THE ASSOCIATED PRESS"}, "source": "The New York Times", "snippet": "The company, based in Fort Lauderdale, Fla., said on Tuesday that it sold 33,069 new vehicles in December.", "web_url": "http://www.nytimes.com/2015/01/07/business/autonation-says-its-sales-rose-12-percent-in-december.html", "slideshow_credits": null, "blog": [], "keywords": [{"rank": "1", "is_major": "Y", "value": "Automobiles", "name": "subject"}, {"rank": "2", "is_major": "Y", "value": "Autonation Inc", "name": "organizations"}], "headline": {"main": "AutoNation Says Its Sales Rose 12 Percent in December", "content_kicker": "Business Briefing", "print_headline": "AutoNation Says Its Sales Rose 12 Percent in December"}}