{"news_desk": "Sports", "print_page": "10", "section_name": "Sports", "subsection_name": "Horse Racing", "byline": {"contributor": "", "original": "By THE ASSOCIATED PRESS", "person": [], "organization": "THE ASSOCIATED PRESS"}, "abstract": "Triple Crown winner American Pharoah is named 2015 horse of year at Eclipse Awards.", "type_of_material": "Brief", "word_count": "84", "lead_paragraph": "Pharoah, the winner of the Triple Crown and the Breeders\u2019 Cup Classic, was named the 2015 horse of the year and the top 3-year-old male at the Eclipse Awards.", "pub_date": "2016-01-17T00:00:00Z", "document_type": "article", "slideshow_credits": null, "headline": {"main": "American Pharoah Honored", "content_kicker": "Sports Briefing | Horse Racing", "print_headline": "American Pharoah Honored"}, "snippet": "Pharoah, the winner of the Triple Crown and the Breeders\u2019 Cup Classic, was named the 2015 horse of the year and the top 3-year-old male at the Eclipse Awards.", "multimedia": [], "web_url": "http://www.nytimes.com/2016/01/17/sports/horse-racing/american-pharoah-honored.html", "keywords": [{"rank": "1", "is_major": "Y", "value": "Horse Racing", "name": "subject"}, {"rank": "2", "is_major": "N", "value": "American Pharoah (Race Horse)", "name": "subject"}, {"rank": "3", "is_major": "Y", "value": "Awards, Decorations and Honors", "name": "subject"}], "blog": [], "_id": "569b279d38f0d80d6e34209d", "source": "The New York Times"}