{"news_desk": "Sports", "print_page": "13", "section_name": "Sports", "subsection_name": "Hockey", "byline": {"contributor": "", "original": "By THE ASSOCIATED PRESS", "person": [], "organization": "THE ASSOCIATED PRESS"}, "abstract": "St Louis Blues will play its first-ever outdoor game when Chicago Blackhawks visit Busch Stadium on Jan 2, 2017.", "type_of_material": "Brief", "word_count": "66", "lead_paragraph": "The St. Louis Blues will host the Chicago Blackhawks in the Winter Classic at Busch Stadium on Jan. 2, the N.H.L. said.", "pub_date": "2016-03-10T00:00:00Z", "document_type": "article", "slideshow_credits": null, "headline": {"main": "St. Louis to Host Blues-Blackhawks Classic", "content_kicker": "Sports Briefing | Hockey", "print_headline": "Blues-Blackhawks Classic"}, "snippet": "The St. Louis Blues will host the Chicago Blackhawks in the Winter Classic at Busch Stadium on Jan. 2, the N.H.L. said.", "multimedia": [], "web_url": "http://www.nytimes.com/2016/03/10/sports/hockey/blues-blackhawks-classic.html", "keywords": [{"rank": "1", "is_major": "Y", "value": "Hockey, Ice", "name": "subject"}, {"rank": "2", "is_major": "Y", "value": "St Louis Blues", "name": "organizations"}, {"rank": "3", "is_major": "Y", "value": "Chicago Blackhawks", "name": "organizations"}], "blog": [], "_id": "56e105f438f0d80718d5668d", "source": "The New York Times"}