{"news_desk": "Editorial", "print_page": "8", "section_name": "Opinion", "subsection_name": "Sunday Review", "byline": {"contributor": "", "original": "By THE EDITORIAL BOARD", "person": [], "organization": "THE EDITORIAL BOARD"}, "abstract": "Editorial welcomes Consumer Financial Protection Bureau's preliminary proposal for protecting working poor from payday lending industry, calling it most important step in agency's four-year history; points to one weakness in proposal, which allows lenders to skip assessment of borrower's ability to pay if loan is $500 or less.", "type_of_material": "Editorial", "word_count": "500", "lead_paragraph": "The Consumer Financial Protection Bureau took the most important step in its four-year history this week.", "pub_date": "2015-03-29T00:00:00Z", "document_type": "article", "slideshow_credits": null, "headline": {"main": "Progress on Payday Lending", "content_kicker": "Editorial", "print_headline": "Progress on Payday Lending", "kicker": "Editorial"}, "snippet": "The Consumer Financial Protection Bureau took the most important step in its four-year history this week.", "multimedia": [{"height": 126, "url": "images/2015/03/28/opinion/29sun2web/29sun2web-thumbWide.jpg", "legacy": {"widewidth": "190", "wideheight": "126", "wide": "images/2015/03/28/opinion/29sun2web/29sun2web-thumbWide.jpg"}, "type": "image", "width": 190, "subtype": "wide"}, {"height": 457, "url": "images/2015/03/28/opinion/29sun2web/29sun2web-articleLarge.jpg", "legacy": {"xlargewidth": "600", "xlargeheight": "457", "xlarge": "images/2015/03/28/opinion/29sun2web/29sun2web-articleLarge.jpg"}, "type": "image", "width": 600, "subtype": "xlarge"}, {"height": 75, "url": "images/2015/03/28/opinion/29sun2web/29sun2web-thumbStandard.jpg", "legacy": {"thumbnailwidth": "75", "thumbnail": "images/2015/03/28/opinion/29sun2web/29sun2web-thumbStandard.jpg", "thumbnailheight": "75"}, "type": "image", "width": 75, "subtype": "thumbnail"}], "web_url": "http://www.nytimes.com/2015/03/29/opinion/sunday/progress-on-payday-lending.html", "keywords": [{"rank": "1", "is_major": "Y", "value": "Consumer Financial Protection Bureau", "name": "organizations"}, {"rank": "2", "is_major": "Y", "value": "Credit and Debt", "name": "subject"}, {"rank": "3", "is_major": "N", "value": "Payday Loans", "name": "subject"}, {"rank": "4", "is_major": "N", "value": "Consumer Protection", "name": "subject"}, {"rank": "5", "is_major": "Y", "value": "Editorials", "name": "subject"}, {"rank": "6", "is_major": "N", "value": "Regulation and Deregulation of Industry", "name": "subject"}], "blog": [], "_id": "5516f33538f0d866c034e5e3", "source": "The New York Times"}