{"news_desk": "Sports", "print_page": "6", "section_name": "Sports", "subsection_name": "Tennis", "byline": {"contributor": "", "original": "By THE ASSOCIATED PRESS", "person": [], "organization": "THE ASSOCIATED PRESS"}, "abstract": "Maria Sharapova defeats Karolina Pliskova in Fed Cup tennis tournament.", "type_of_material": "Brief", "word_count": "42", "lead_paragraph": "Maria Sharapova defeated Karolina Pliskova, 6-3, 6-4, to pull Russia into a 1-1 tie with Czech Republic, the defending champion, in the Fed Cup final.", "pub_date": "2015-11-15T00:00:00Z", "document_type": "article", "slideshow_credits": null, "headline": {"main": "Russia Draws Even at Fed Cup", "content_kicker": "Sports Briefing | Tennis", "print_headline": "Russia Draws Even at Fed Cup"}, "snippet": "Maria Sharapova defeated Karolina Pliskova, 6-3, 6-4, to pull Russia into a 1-1 tie with Czech Republic, the defending champion, in the Fed Cup final.", "multimedia": [], "web_url": "http://www.nytimes.com/2015/11/15/sports/tennis/russia-draws-even-at-fed-cup.html", "keywords": [{"rank": "1", "is_major": "Y", "value": "Tennis", "name": "subject"}, {"rank": "2", "is_major": "N", "value": "Sharapova, Maria", "name": "persons"}, {"rank": "3", "is_major": "N", "value": "Pliskova, Karolina", "name": "persons"}], "blog": [], "_id": "5648156d38f0d87eefe471cd", "source": "The New York Times"}