{"news_desk": "Business", "print_page": null, "section_name": "Business Day", "subsection_name": "International Business", "byline": {"original": "By REUTERS", "person": [], "organization": "REUTERS"}, "abstract": null, "type_of_material": "News", "word_count": "267", "lead_paragraph": "The legislation, which takes effect this month, permits officials to block internet access to \u201cillegal dispatcher services.\u201d", "pub_date": "2016-07-14T00:00:00Z", "document_type": "article", "slideshow_credits": null, "headline": {"main": "Uber to Suspend Operations in Hungary Over New Law"}, "snippet": "The legislation, which takes effect this month, permits officials to block internet access to \u201cillegal dispatcher services.\u201d...", "multimedia": [{"height": 126, "url": "images/2016/07/14/business/14HUNGARY-web/14HUNGARY-web-thumbWide.jpg", "legacy": {"widewidth": "190", "wideheight": "126", "wide": "images/2016/07/14/business/14HUNGARY-web/14HUNGARY-web-thumbWide.jpg"}, "type": "image", "width": 190, "subtype": "wide"}, {"height": 403, "url": "images/2016/07/14/business/14HUNGARY-web/14HUNGARY-web-articleLarge.jpg", "legacy": {"xlargewidth": "600", "xlargeheight": "403", "xlarge": "images/2016/07/14/business/14HUNGARY-web/14HUNGARY-web-articleLarge.jpg"}, "type": "image", "width": 600, "subtype": "xlarge"}, {"height": 75, "url": "images/2016/07/14/business/14HUNGARY-web/14HUNGARY-web-thumbStandard.jpg", "legacy": {"thumbnailwidth": "75", "thumbnail": "images/2016/07/14/business/14HUNGARY-web/14HUNGARY-web-thumbStandard.jpg", "thumbnailheight": "75"}, "type": "image", "width": 75, "subtype": "thumbnail"}], "web_url": "http://www.nytimes.com/2016/07/14/business/international/uber-hungary-taxi-suspension.html", "keywords": [{"rank": "1", "is_major": "N", "value": "Car Services and Livery Cabs", "name": "subject"}, {"rank": "2", "is_major": "N", "value": "Law and Legislation", "name": "subject"}, {"rank": "3", "is_major": "N", "value": "Uber Technologies Inc", "name": "organizations"}, {"rank": "4", "is_major": "N", "value": "Hungary", "name": "glocations"}], "blog": [], "_id": "57864f1c38f0d804dfd9bc19", "source": "The New York Times"}