{"term": "restaurants", "price": "$$", "coordinates": {"longitude": 115.88953, "latitude": -31.91823}, "image_url": "https://s3-media3.fl.yelpcdn.com/bphoto/w73UaeIaiFlcou2O4oxknQ/o.jpg", "id": "cecchis-inglewood", "rating": 4.5, "name": "Cecchi's", "is_claimed": true, "location": {"address1": "965 Beaufort St", "address2": "", "zip_code": "6052", "country": "AU", "state": "WA", "city": "Inglewood", "address3": ""}, "is_closed": false, "phone": "+61892716366", "review_count": 29, "photos": ["https://s3-media1.fl.yelpcdn.com/bphoto/w73UaeIaiFlcou2O4oxknQ/o.jpg", "https://s3-media4.fl.yelpcdn.com/bphoto/DZIXBTTtHjgmafooX7ZngA/o.jpg", "https://s3-media1.fl.yelpcdn.com/bphoto/KQFKAiTEMzg5qQB3je-TNA/o.jpg"], "hours": [{"open": [{"day": 1, "is_overnight": false, "end": "2300", "start": "1800"}, {"day": 2, "is_overnight": false, "end": "1500", "start": "0730"}, {"day": 2, "is_overnight": false, "end": "2300", "start": "1800"}, {"day": 3, "is_overnight": false, "end": "1500", "start": "0730"}, {"day": 3, "is_overnight": false, "end": "2300", "start": "1800"}, {"day": 4, "is_overnight": false, "end": "1500", "start": "0730"}, {"day": 4, "is_overnight": false, "end": "2300", "start": "1800"}, {"day": 5, "is_overnight": false, "end": "1500", "start": "0730"}, {"day": 5, "is_overnight": false, "end": "2300", "start": "1800"}, {"day": 6, "is_overnight": false, "end": "1500", "start": "0730"}], "is_open_now": true, "hours_type": "REGULAR"}], "categories": [{"alias": "mediterranean", "title": "Mediterranean"}, {"alias": "modern_european", "title": "Modern European"}], "url": "https://www.yelp.com/biz/cecchis-inglewood?adjust_creative=92p07_JjKyriZTQxAXRiKQ&utm_campaign=yelp_api_v3&utm_medium=api_v3_business_lookup&utm_source=92p07_JjKyriZTQxAXRiKQ"}