{"coordinates": {"longitude": 151.2136383, "latitude": -33.8859596}, "image_url": "https://s3-media3.fl.yelpcdn.com/bphoto/jmOyyO1V_9UUXen2wle0rw/o.jpg", "id": "surry-hills-library-surry-hills", "is_claimed": false, "name": "Surry Hills Library", "rating": 4.0, "photos": ["https://s3-media3.fl.yelpcdn.com/bphoto/jmOyyO1V_9UUXen2wle0rw/o.jpg", "https://s3-media2.fl.yelpcdn.com/bphoto/QhNb3KArxLmTP6rA9KaP7g/o.jpg", "https://s3-media3.fl.yelpcdn.com/bphoto/tTBVvbMC-wADAsC_Hjb_QQ/o.jpg"], "is_closed": false, "phone": "+61283746250", "term": "attractions", "review_count": 15, "location": {"address1": "405 Crown St", "address2": null, "zip_code": "2010", "country": "AU", "state": "NSW", "city": "Surry Hills", "address3": null}, "hours": [{"open": [{"day": 0, "is_overnight": false, "end": "1800", "start": "1000"}, {"day": 1, "is_overnight": false, "end": "2000", "start": "1000"}, {"day": 2, "is_overnight": false, "end": "1800", "start": "1000"}, {"day": 3, "is_overnight": false, "end": "2100", "start": "1000"}, {"day": 4, "is_overnight": false, "end": "1800", "start": "1000"}, {"day": 5, "is_overnight": false, "end": "1600", "start": "1000"}, {"day": 6, "is_overnight": false, "end": "1600", "start": "1000"}], "is_open_now": true, "hours_type": "REGULAR"}], "categories": [{"alias": "libraries", "title": "Libraries"}], "url": "https://www.yelp.com/biz/surry-hills-library-surry-hills?adjust_creative=92p07_JjKyriZTQxAXRiKQ&utm_campaign=yelp_api_v3&utm_medium=api_v3_business_lookup&utm_source=92p07_JjKyriZTQxAXRiKQ"}