{"news_desk": "Business Day", "print_page": null, "section_name": "Business Day", "subsection_name": null, "byline": [], "abstract": null, "type_of_material": "Slideshow", "word_count": "20", "lead_paragraph": "Six decades-old presses are being refurbished at a plant in New Jersey to meet the exploding demand for vinyl records.", "pub_date": "2015-09-15T00:00:00Z", "document_type": "multimedia", "slideshow_credits": null, "headline": {"main": "A Vinyl LP Frenzy"}, "snippet": "Six decades-old presses are being refurbished at a plant in New Jersey to meet the exploding demand for vinyl records.", "multimedia": [{"height": 126, "url": "images/2015/09/15/business/VINYL-slide-JLS7/VINYL-slide-JLS7-thumbWide-v2.jpg", "legacy": {"widewidth": "190", "wideheight": "126", "wide": "images/2015/09/15/business/VINYL-slide-JLS7/VINYL-slide-JLS7-thumbWide-v2.jpg"}, "type": "image", "width": 190, "subtype": "wide"}, {"height": 401, "url": "images/2015/09/15/business/VINYL-slide-JLS7/VINYL-slide-JLS7-articleLarge.jpg", "legacy": {"xlargewidth": "600", "xlargeheight": "401", "xlarge": "images/2015/09/15/business/VINYL-slide-JLS7/VINYL-slide-JLS7-articleLarge.jpg"}, "type": "image", "width": 600, "subtype": "xlarge"}, {"height": 75, "url": "images/2015/09/15/business/VINYL-slide-JLS7/VINYL-slide-JLS7-thumbStandard.jpg", "legacy": {"thumbnailwidth": "75", "thumbnail": "images/2015/09/15/business/VINYL-slide-JLS7/VINYL-slide-JLS7-thumbStandard.jpg", "thumbnailheight": "75"}, "type": "image", "width": 75, "subtype": "thumbnail"}], "web_url": "http://www.nytimes.com/slideshow/2015/09/15/business/tk-tk.html", "keywords": [{"rank": "1", "is_major": "N", "value": "Audio Recordings, Downloads and Streaming", "name": "subject"}], "blog": [], "_id": "55f735f238f0d866752b57d3", "source": "The New York Times"}