{"news_desk": "Fashion & Style / Men\u2019s Style", "print_page": null, "subsection_name": "Men\u2019s Style", "section_name": "Fashion & Style", "byline": [], "abstract": null, "type_of_material": "Slideshow", "word_count": "8", "keywords": [{"rank": "1", "value": "Warhol, Andy", "is_major": "N", "name": "persons"}, {"rank": "2", "value": "Davis, Sammy Jr", "is_major": "N", "name": "persons"}, {"rank": "3", "value": "Garland, Judy", "is_major": "N", "name": "persons"}], "lead_paragraph": "A sampling of memorabilia from Brett Ratner\u2019s auction.", "pub_date": "2016-11-01T20:11:56Z", "document_type": "multimedia", "source": "The New York Times", "snippet": "A sampling of memorabilia from Brett Ratner\u2019s auction....", "multimedia": [{"height": 126, "subtype": "wide", "legacy": {"widewidth": "190", "wide": "images/2016/11/04/fashion/04MS-RATNER1-SS/04MS-RATNER1-SS-thumbWide.jpg", "wideheight": "126"}, "type": "image", "width": 190, "url": "images/2016/11/04/fashion/04MS-RATNER1-SS/04MS-RATNER1-SS-thumbWide.jpg"}, {"height": 747, "subtype": "xlarge", "legacy": {"xlargewidth": "600", "xlargeheight": "747", "xlarge": "images/2016/11/04/fashion/04MS-RATNER1-SS/04MS-RATNER1-SS-articleLarge.jpg"}, "type": "image", "width": 600, "url": "images/2016/11/04/fashion/04MS-RATNER1-SS/04MS-RATNER1-SS-articleLarge.jpg"}, {"height": 75, "subtype": "thumbnail", "legacy": {"thumbnailwidth": "75", "thumbnail": "images/2016/11/04/fashion/04MS-RATNER1-SS/04MS-RATNER1-SS-thumbStandard.jpg", "thumbnailheight": "75"}, "type": "image", "width": 75, "url": "images/2016/11/04/fashion/04MS-RATNER1-SS/04MS-RATNER1-SS-thumbStandard.jpg"}], "web_url": "http://www.nytimes.com/slideshow/2016/11/04/fashion/mens-style/brett-ratner-auction-hollywood.html", "slideshow_credits": "Glen E. Friedman/Glen E. Friedman Archive, via Paddle8", "blog": [], "_id": "5818f7167c459f606398cfc5", "headline": {"main": "A \u2018High-End Hoarder\u2019 Sells His Stuff"}}