{"news_desk": "Sports", "print_page": "4", "subsection_name": null, "section_name": "Sports", "byline": {"original": "By THE ASSOCIATED PRESS", "person": [], "organization": "THE ASSOCIATED PRESS"}, "abstract": null, "type_of_material": "News", "word_count": "563", "keywords": [{"rank": "1", "value": "Alpine Skiing", "is_major": "N", "name": "subject"}, {"rank": "2", "value": "World Cup (Skiing)", "is_major": "N", "name": "subject"}, {"rank": "3", "value": "Ganong, Travis (1988- )", "is_major": "N", "name": "persons"}, {"rank": "4", "value": "Nyman, Steven", "is_major": "N", "name": "persons"}, {"rank": "5", "value": "Giraud Moine, Valentin", "is_major": "N", "name": "persons"}, {"rank": "6", "value": "Basketball", "is_major": "N", "name": "subject"}, {"rank": "7", "value": "Soccer", "is_major": "N", "name": "subject"}, {"rank": "8", "value": "Baseball", "is_major": "N", "name": "subject"}], "lead_paragraph": "Travis Ganong won a men\u2019s World Cup downhill race after his American teammate Steven Nyman and the French skier Valentin Giraud Moine were airlifted to hospitals with serious injuries.", "pub_date": "2017-01-28T04:51:55+0000", "document_type": "article", "source": "The New York Times", "snippet": "Travis Ganong won a men\u2019s World Cup downhill race after his American teammate Steven Nyman and the French skier Valentin Giraud Moine were airlifted to hospitals with serious injuries....", "multimedia": [], "web_url": "http://www.nytimes.com/2017/01/27/sports/american-wins-world-cup-downhill-in-germany-2-skiers-badly-hurt.html", "slideshow_credits": null, "blog": [], "_id": "588c237095d0e0392607d488", "headline": {"main": "American Wins World Cup Downhill in Germany; 2 Skiers Badly Hurt", "content_kicker": "Sports Briefing", "print_headline": "Winter Sports; American Wins Downhill; 2 Skiers Badly Hurt", "kicker": "Sports Briefing"}}