{"news_desk": "U.S.", "print_page": null, "section_name": "U.S.", "subsection_name": null, "byline": {"original": "By REUTERS", "person": [], "organization": "REUTERS"}, "abstract": null, "type_of_material": "Video", "word_count": "33", "lead_paragraph": "Mathew D. Staver, the lawyer for the Kentucky clerk Kim Davis, spoke on Tuesday about his client\u2019s release after she was jailed for defying a court\u2019s order that she issue same-sex marriage licenses.", "pub_date": "2015-09-08T15:36:27Z", "document_type": "multimedia", "slideshow_credits": null, "headline": {"main": "Lawyer Discusses Kim Davis\u2019s Release"}, "snippet": "Mathew D. Staver, the lawyer for the Kentucky clerk Kim Davis, spoke on Tuesday about his client\u2019s release after she was jailed for defying a court\u2019s order that she issue same-sex marriage licenses.", "multimedia": [{"height": 126, "url": "images/2015/09/08/us/09KENTUCKY/09KENTUCKY-thumbWide.jpg", "legacy": {"widewidth": "190", "wideheight": "126", "wide": "images/2015/09/08/us/09KENTUCKY/09KENTUCKY-thumbWide.jpg"}, "type": "image", "width": 190, "subtype": "wide"}, {"height": 400, "url": "images/2015/09/08/us/09KENTUCKY/09KENTUCKY-articleLarge.jpg", "legacy": {"xlargewidth": "600", "xlargeheight": "400", "xlarge": "images/2015/09/08/us/09KENTUCKY/09KENTUCKY-articleLarge.jpg"}, "type": "image", "width": 600, "subtype": "xlarge"}, {"height": 75, "url": "images/2015/09/08/us/09KENTUCKY/09KENTUCKY-thumbStandard.jpg", "legacy": {"thumbnailwidth": "75", "thumbnail": "images/2015/09/08/us/09KENTUCKY/09KENTUCKY-thumbStandard.jpg", "thumbnailheight": "75"}, "type": "image", "width": 75, "subtype": "thumbnail"}], "web_url": "http://www.nytimes.com/video/us/100000003897383/lawyer-discusses-kim-daviss-release.html", "keywords": [{"rank": "1", "is_major": "N", "value": "Legal Profession", "name": "subject"}, {"rank": "2", "is_major": "N", "value": "Kentucky", "name": "glocations"}], "blog": [], "_id": "55ef38da38f0d867b4c89642", "source": "The New York Times"}