{"news_desk": "Sports", "print_page": "14", "section_name": "Sports", "subsection_name": null, "byline": {"contributor": "", "original": "By THE ASSOCIATED PRESS", "person": [], "organization": "THE ASSOCIATED PRESS"}, "abstract": "German ski jumper Severin Freund wins sixth victory of season during World Cup event in Finland.", "type_of_material": "Brief", "word_count": "48", "lead_paragraph": "Severin Freund leapt to a victory in Kuopio, Finland. The World Cup leader, Petr Prevc of Slovenia, managed only a 17th-place finish and dropped to third in the standings.", "pub_date": "2015-03-11T00:00:00Z", "document_type": "article", "slideshow_credits": null, "headline": {"main": "Sixth Win for German Ski Jumper", "content_kicker": "Sports Briefing | Winter Sports", "print_headline": "Sixth Win for German Ski Jumper"}, "snippet": "Severin Freund leapt to a victory in Kuopio, Finland. The World Cup leader, Petr Prevc of Slovenia, managed only a 17th-place finish and dropped to third in the standings.", "multimedia": [], "web_url": "http://www.nytimes.com/2015/03/11/sports/sixth-win-for-german-ski-jumper.html", "keywords": [{"rank": "1", "is_major": "Y", "value": "Ski Jumping", "name": "subject"}, {"rank": "2", "is_major": "Y", "value": "Freund, Severin", "name": "persons"}], "blog": [], "_id": "54ffdae538f0d83c4ddeafd9", "source": "The New York Times"}