{"news_desk": "Foreign", "print_page": "5", "section_name": "World", "subsection_name": "Americas", "byline": {"contributor": "", "original": "By THE ASSOCIATED PRESS", "person": [], "organization": "THE ASSOCIATED PRESS"}, "abstract": "Canadian helicopter pilot David Wood dies after landing on remote ice shelf in Antarctica.", "type_of_material": "Brief", "word_count": "100", "lead_paragraph": "The pilot, David Wood, was working on a fuel-loading operation on the remote ice shelf on Monday when he got out of the helicopter and fell more than 60 feet.", "pub_date": "2016-01-13T00:00:00Z", "document_type": "article", "slideshow_credits": null, "headline": {"main": "Canada: Pilot Dies in Antarctica", "content_kicker": "World Briefing", "print_headline": "The Americas; Canada: Pilot Dies in Antarctica"}, "snippet": "The pilot, David Wood, was working on a fuel-loading operation on the remote ice shelf on Monday when he got out of the helicopter and fell more than 60 feet.", "multimedia": [], "web_url": "http://www.nytimes.com/2016/01/13/world/americas/canada-pilot-dies-in-antarctica.html", "keywords": [{"rank": "1", "is_major": "Y", "value": "Aviation Accidents, Safety and Disasters", "name": "subject"}, {"rank": "2", "is_major": "Y", "value": "Antarctic Regions", "name": "glocations"}, {"rank": "3", "is_major": "Y", "value": "Wood, David (d 2016)", "name": "persons"}, {"rank": "4", "is_major": "Y", "value": "Canada", "name": "glocations"}, {"rank": "5", "is_major": "N", "value": "Helicopters", "name": "subject"}, {"rank": "6", "is_major": "N", "value": "Deaths (Fatalities)", "name": "subject"}], "blog": [], "_id": "5695a1fc38f0d83e7cfe040b", "source": "The New York Times"}