{"news_desk": "Society", "print_page": "15", "section_name": "Fashion & Style", "subsection_name": "Weddings", "byline": [], "abstract": null, "type_of_material": "News", "word_count": "227", "lead_paragraph": "The bride and groom met at Harvard Law School.", "pub_date": "2016-04-10T00:00:00Z", "document_type": "article", "slideshow_credits": null, "headline": {"main": "Corinne Snow, David Denton Jr.", "print_headline": "Corinne Snow,  David Denton Jr."}, "snippet": "The bride and groom met at Harvard Law School.", "multimedia": [], "web_url": "http://www.nytimes.com/2016/04/10/fashion/weddings/corinne-snow-david-denton-jr.html", "keywords": [{"rank": "1", "is_major": "N", "value": "Weddings and Engagements", "name": "subject"}], "blog": [], "_id": "5709d34a38f0d84b5a706224", "source": "The New York Times"}