{"news_desk": "Letters", "print_page": "24", "subsection_name": null, "section_name": "Opinion", "byline": [], "abstract": null, "type_of_material": "Letter", "word_count": "561", "keywords": [{"rank": "1", "value": "Conflicts of Interest", "is_major": "N", "name": "subject"}, {"rank": "2", "value": "Trump, Donald J", "is_major": "N", "name": "persons"}], "lead_paragraph": "Readers discuss the potential conflicts that Mr. Trump faces because of his international business interests.", "pub_date": "2016-12-01T18:13:45+0000", "document_type": "article", "source": "The New York Times", "snippet": "Readers discuss the potential conflicts that Mr. Trump faces because of his international business interests....", "multimedia": [], "web_url": "http://www.nytimes.com/2016/12/01/opinion/donald-trumps-businesses-and-the-presidency.html", "slideshow_credits": null, "blog": [], "_id": "5840685e95d0e0392607384a", "headline": {"main": "Donald Trump\u2019s Businesses and the Presidency", "content_kicker": "Letters", "print_headline": "Trump\u2019s Business, and the Nation\u2019s", "kicker": "Letters"}}