{"news_desk": "Letters", "print_page": "20", "section_name": "Opinion", "subsection_name": null, "byline": [], "abstract": null, "type_of_material": "Letter", "word_count": "584", "lead_paragraph": "\u201cNothing can surpass a great lecture if done correctly with passion, commitment, interaction and intensity,\u201d one reader writes.", "pub_date": "2015-10-26T00:00:00Z", "document_type": "article", "slideshow_credits": null, "headline": {"main": "The Value of College Lectures", "content_kicker": "Letters", "print_headline": "The Value of College Lectures", "kicker": "Letters"}, "snippet": "\u201cNothing can surpass a great lecture if done correctly with passion, commitment, interaction and intensity,\u201d one reader writes.", "multimedia": [{"height": 126, "url": "images/2015/10/26/opinion/26Llectures-web/26Llectures-web-thumbWide-v2.jpg", "legacy": {"widewidth": "190", "wideheight": "126", "wide": "images/2015/10/26/opinion/26Llectures-web/26Llectures-web-thumbWide-v2.jpg"}, "type": "image", "width": 190, "subtype": "wide"}, {"height": 393, "url": "images/2015/10/26/opinion/26Llectures-web/26Llectures-web-articleLarge.jpg", "legacy": {"xlargewidth": "600", "xlargeheight": "393", "xlarge": "images/2015/10/26/opinion/26Llectures-web/26Llectures-web-articleLarge.jpg"}, "type": "image", "width": 600, "subtype": "xlarge"}, {"height": 75, "url": "images/2015/10/26/opinion/26Llectures-web/26Llectures-web-thumbStandard-v2.jpg", "legacy": {"thumbnailwidth": "75", "thumbnail": "images/2015/10/26/opinion/26Llectures-web/26Llectures-web-thumbStandard-v2.jpg", "thumbnailheight": "75"}, "type": "image", "width": 75, "subtype": "thumbnail"}], "web_url": "http://www.nytimes.com/2015/10/26/opinion/the-value-of-college-lectures.html", "keywords": [{"rank": "1", "is_major": "N", "value": "Colleges and Universities", "name": "subject"}], "blog": [], "_id": "562dd3ea38f0d8190048327c", "source": "The New York Times"}