{"news_desk": "Letters", "print_page": "22", "subsection_name": null, "section_name": "Opinion", "byline": [], "abstract": null, "type_of_material": "Letter", "word_count": "222", "keywords": [{"rank": "1", "value": "Pruitt, Scott", "is_major": "N", "name": "persons"}, {"rank": "2", "value": "Trump, Donald J", "is_major": "N", "name": "persons"}, {"rank": "3", "value": "Environmental Protection Agency", "is_major": "N", "name": "organizations"}, {"rank": "4", "value": "United States Politics and Government", "is_major": "N", "name": "subject"}], "lead_paragraph": "The Natural Resources Defense Council writes that Scott Pruitt would do lasting damage to environmental protections.", "pub_date": "2017-02-13T08:21:03+0000", "document_type": "article", "source": "The New York Times", "snippet": "The Natural Resources Defense Council writes that Scott Pruitt would do lasting damage to environmental protections....", "multimedia": [{"height": 126, "subtype": "wide", "legacy": {"widewidth": "190", "wide": "images/2017/02/06/us/06epa/06epa-thumbWide.jpg", "wideheight": "126"}, "type": "image", "width": 190, "url": "images/2017/02/06/us/06epa/06epa-thumbWide.jpg"}, {"height": 400, "subtype": "xlarge", "legacy": {"xlargewidth": "600", "xlargeheight": "400", "xlarge": "images/2017/02/06/us/06epa/06epa-articleLarge.jpg"}, "type": "image", "width": 600, "url": "images/2017/02/06/us/06epa/06epa-articleLarge.jpg"}, {"height": 75, "subtype": "thumbnail", "legacy": {"thumbnailwidth": "75", "thumbnail": "images/2017/02/06/us/06epa/06epa-thumbStandard.jpg", "thumbnailheight": "75"}, "type": "image", "width": 75, "url": "images/2017/02/06/us/06epa/06epa-thumbStandard.jpg"}], "web_url": "http://www.nytimes.com/2017/02/13/opinion/cutting-at-the-epa.html", "slideshow_credits": null, "blog": [], "_id": "58a16c747c459f2525d1bfec", "headline": {"main": "Cutting at the E.P.A.", "content_kicker": "Letter", "print_headline": "Cutting at the E.P.A.", "kicker": "Letter"}}