{"news_desk": "Letters", "print_page": "22", "subsection_name": null, "section_name": "Opinion", "byline": [], "abstract": null, "type_of_material": "Letter", "word_count": "163", "keywords": [{"rank": "1", "value": "Legal Profession", "is_major": "N", "name": "subject"}], "lead_paragraph": "The Institute for Innovation in Prosecution writes that prosecutors need to recognize the potential for redemption.", "pub_date": "2017-02-13T08:21:02+0000", "document_type": "article", "source": "The New York Times", "snippet": "The Institute for Innovation in Prosecution writes that prosecutors need to recognize the potential for redemption....", "multimedia": [], "web_url": "http://www.nytimes.com/2017/02/13/opinion/a-task-for-prosecutors.html", "slideshow_credits": null, "blog": [], "_id": "58a16c747c459f2525d1bfeb", "headline": {"main": "A Task for Prosecutors", "content_kicker": "Letter", "print_headline": "A Task for Prosecutors", "kicker": "Letter"}}