{"price": "$$", "coordinates": {"longitude": -80.842288, "latitude": 35.199889}, "image_url": "https://s3-media3.fl.yelpcdn.com/bphoto/QizSPZ4s5UoXVJJGmxWrqQ/o.jpg", "id": "lebowskis-neighborhood-grill-charlotte", "is_claimed": true, "name": "Lebowski's Neighborhood Grill", "rating": 4.5, "photos": ["https://s3-media3.fl.yelpcdn.com/bphoto/QizSPZ4s5UoXVJJGmxWrqQ/o.jpg", "https://s3-media2.fl.yelpcdn.com/bphoto/svGIjUTSbVMhjKazrT470Q/o.jpg", "https://s3-media4.fl.yelpcdn.com/bphoto/Y4lNeyxQ9wcGB30-XYufTQ/o.jpg"], "is_closed": false, "phone": "+17043701177", "term": "restaurants", "review_count": 254, "location": {"address1": "1524 East Blvd", "address2": "", "zip_code": "28203", "country": "US", "state": "NC", "city": "Charlotte", "address3": ""}, "hours": [{"open": [{"day": 0, "is_overnight": true, "end": "0030", "start": "1100"}, {"day": 1, "is_overnight": true, "end": "0030", "start": "1100"}, {"day": 2, "is_overnight": true, "end": "0030", "start": "1100"}, {"day": 3, "is_overnight": true, "end": "0030", "start": "1100"}, {"day": 4, "is_overnight": true, "end": "0200", "start": "1100"}, {"day": 5, "is_overnight": true, "end": "0200", "start": "1100"}, {"day": 6, "is_overnight": false, "end": "2200", "start": "1100"}], "is_open_now": false, "hours_type": "REGULAR"}], "categories": [{"title": "Pubs", "alias": "pubs"}, {"title": "Sports Bars", "alias": "sportsbars"}, {"title": "American (Traditional)", "alias": "tradamerican"}], "url": "https://www.yelp.com/biz/lebowskis-neighborhood-grill-charlotte?adjust_creative=92p07_JjKyriZTQxAXRiKQ&utm_campaign=yelp_api_v3&utm_medium=api_v3_business_lookup&utm_source=92p07_JjKyriZTQxAXRiKQ"}