{"news_desk": "Business", "print_page": "4", "section_name": "Business Day", "subsection_name": null, "byline": {"contributor": "", "original": "By REUTERS", "person": [], "organization": "REUTERS"}, "abstract": "Alcoa reports earning profit in first quarter, with net income of $195 million, compared with loss of $178 million year earlier.", "type_of_material": "News", "word_count": "484", "lead_paragraph": "Alcoa said it expected the world aluminum market to have a surplus of 326,000 metric tons in 2015.", "pub_date": "2015-04-09T00:00:00Z", "document_type": "article", "slideshow_credits": null, "headline": {"main": "Alcoa Posts Profit on Shift in Operations ", "print_headline": "Alcoa Posts Profit on Shift in Operations"}, "snippet": "Alcoa said it expected the world aluminum market to have a surplus of 326,000 metric tons in 2015.", "multimedia": [{"height": 126, "url": "images/2015/04/09/business/09ALCOA/09ALCOA-thumbWide.jpg", "legacy": {"widewidth": "190", "wideheight": "126", "wide": "images/2015/04/09/business/09ALCOA/09ALCOA-thumbWide.jpg"}, "type": "image", "width": 190, "subtype": "wide"}, {"height": 400, "url": "images/2015/04/09/business/09ALCOA/09ALCOA-articleLarge.jpg", "legacy": {"xlargewidth": "600", "xlargeheight": "400", "xlarge": "images/2015/04/09/business/09ALCOA/09ALCOA-articleLarge.jpg"}, "type": "image", "width": 600, "subtype": "xlarge"}, {"height": 75, "url": "images/2015/04/09/business/09ALCOA/09ALCOA-thumbStandard.jpg", "legacy": {"thumbnailwidth": "75", "thumbnail": "images/2015/04/09/business/09ALCOA/09ALCOA-thumbStandard.jpg", "thumbnailheight": "75"}, "type": "image", "width": 75, "subtype": "thumbnail"}], "web_url": "http://www.nytimes.com/2015/04/09/business/alcoa-posts-profit-on-shift-in-operations.html", "keywords": [{"rank": "1", "is_major": "Y", "value": "Alcoa Inc", "name": "organizations"}, {"rank": "2", "is_major": "N", "value": "Company Reports", "name": "subject"}], "blog": [], "_id": "5525c1aa38f0d8148de1fd04", "source": "The New York Times"}