{"news_desk": "World", "print_page": null, "section_name": "World", "subsection_name": null, "byline": [], "abstract": null, "type_of_material": "Interactive Feature", "word_count": null, "lead_paragraph": "En la semana de la Cumbre del Clima en Par\u00eds, hemos reunido respuestas breves a preguntas frecuentes sobre el cambio clim\u00e1tico.", "pub_date": "2015-12-02T00:00:00Z", "document_type": "multimedia", "slideshow_credits": null, "headline": {"main": "Respuestas breves a las 10 preguntas m\u00e1s importantes sobre el cambio clim\u00e1tico"}, "snippet": "En la semana de la Cumbre del Clima en Par\u00eds, hemos reunido respuestas breves a preguntas frecuentes sobre el cambio clim\u00e1tico.", "multimedia": [], "web_url": "http://www.nytimes.com/interactive/2015/12/02/world/preguntas-respuestas-cambio-climatico-cumbre-paris.html", "keywords": [], "blog": [], "_id": "565f488038f0d80f6038b235", "source": "The New York Times"}