{"news_desk": "Culture", "print_page": null, "subsection_name": null, "section_name": "Books", "byline": {"original": "By THE NEW YORK TIMES", "person": [], "organization": "THE NEW YORK TIMES"}, "abstract": null, "type_of_material": "News", "word_count": "1077", "keywords": [{"rank": "1", "value": "Books and Literature", "is_major": "N", "name": "subject"}, {"rank": "2", "value": "Presidential Election of 2016", "is_major": "N", "name": "subject"}, {"rank": "3", "value": "Packer, George", "is_major": "N", "name": "persons"}, {"rank": "4", "value": "Hochschild, Arlie Russell", "is_major": "N", "name": "persons"}, {"rank": "5", "value": "Vance, J D", "is_major": "N", "name": "persons"}, {"rank": "6", "value": "Frank, Thomas", "is_major": "N", "name": "persons"}, {"rank": "7", "value": "Isenberg, Nancy", "is_major": "N", "name": "persons"}, {"rank": "8", "value": "Trump, Donald J", "is_major": "N", "name": "persons"}, {"rank": "9", "value": "Judis, John B", "is_major": "N", "name": "persons"}], "lead_paragraph": "Our critics and reviewers on books that analyze the shifts that drove one of the most stunning political upsets in the nation\u2019s history.", "pub_date": "2016-11-09T19:29:41Z", "document_type": "article", "source": "The New York Times", "snippet": "Our critics and reviewers on books that analyze the shifts that drove one of the most stunning political upsets in the nation\u2019s history....", "multimedia": [{"height": 126, "subtype": "wide", "legacy": {"widewidth": "190", "wide": "images/2013/05/29/arts/29BOOK/29BOOK-thumbWide-v4.jpg", "wideheight": "126"}, "type": "image", "width": 190, "url": "images/2013/05/29/arts/29BOOK/29BOOK-thumbWide-v4.jpg"}, {"height": 899, "subtype": "xlarge", "legacy": {"xlargewidth": "600", "xlargeheight": "899", "xlarge": "images/2013/05/29/arts/29BOOK/29BOOK-articleLarge-v4.jpg"}, "type": "image", "width": 600, "url": "images/2013/05/29/arts/29BOOK/29BOOK-articleLarge-v4.jpg"}, {"height": 75, "subtype": "thumbnail", "legacy": {"thumbnailwidth": "75", "thumbnail": "images/2013/05/29/arts/29BOOK/29BOOK-thumbStandard-v4.jpg", "thumbnailheight": "75"}, "type": "image", "width": 75, "url": "images/2013/05/29/arts/29BOOK/29BOOK-thumbStandard-v4.jpg"}], "web_url": "http://www.nytimes.com/2016/11/10/books/6-books-to-help-understand-trumps-win.html", "slideshow_credits": null, "blog": [], "_id": "5823792f7c459f6a5fccd1d3", "headline": {"main": "6 Books to Help Understand Trump\u2019s Win"}}