{"review_count": 17, "price": "\u20ac\u20ac", "coordinates": {"longitude": 2.35212, "latitude": 48.84754}, "image_url": "https://s3-media2.fl.yelpcdn.com/bphoto/zyRPZ-mjUdfggT3x2tw0Vw/o.jpg", "phone": "+33143544762", "rating": 4.0, "name": "Grand Action", "is_claimed": false, "location": {"address2": "", "address1": "5 rue des \u00e9coles", "city": "Paris", "country": "FR", "state": "75", "zip_code": "75005", "address3": ""}, "is_closed": false, "id": "grand-action-paris", "term": "attractions", "photos": ["https://s3-media2.fl.yelpcdn.com/bphoto/zyRPZ-mjUdfggT3x2tw0Vw/o.jpg", "https://s3-media4.fl.yelpcdn.com/bphoto/CAAY_s2ssniUkoxqfAJ9ZA/o.jpg", "https://s3-media3.fl.yelpcdn.com/bphoto/MYS8HmXP3EnPfxBn5wwsKA/o.jpg"], "hours": [{"open": [{"day": 0, "is_overnight": false, "end": "0000", "start": "1400"}, {"day": 1, "is_overnight": false, "end": "0000", "start": "1400"}, {"day": 2, "is_overnight": false, "end": "0000", "start": "1400"}, {"day": 3, "is_overnight": false, "end": "0000", "start": "1400"}, {"day": 4, "is_overnight": false, "end": "0000", "start": "1400"}, {"day": 5, "is_overnight": false, "end": "0000", "start": "1400"}, {"day": 6, "is_overnight": false, "end": "0000", "start": "1400"}], "is_open_now": false, "hours_type": "REGULAR"}], "categories": [{"title": "Cinema", "alias": "movietheaters"}], "url": "https://www.yelp.com/biz/grand-action-paris?adjust_creative=92p07_JjKyriZTQxAXRiKQ&utm_campaign=yelp_api_v3&utm_medium=api_v3_business_lookup&utm_source=92p07_JjKyriZTQxAXRiKQ"}