{"news_desk": "Letters", "print_page": "22", "subsection_name": null, "section_name": "Opinion", "byline": [], "abstract": null, "type_of_material": "Letter", "word_count": "127", "keywords": [{"rank": "1", "value": "Movies", "is_major": "N", "name": "subject"}, {"rank": "2", "value": "Night Moves (Movie)", "is_major": "N", "name": "creative_works"}, {"rank": "3", "value": "The Conversation (Movie)", "is_major": "N", "name": "creative_works"}], "lead_paragraph": "A reader, praising a tribute to double features, puts two Gene Hackman films at the top of her wish list.", "pub_date": "2016-08-23T04:00:00+0000", "document_type": "article", "source": "The New York Times", "snippet": "A reader, praising a tribute to double features, puts two Gene Hackman films at the top of her wish list....", "multimedia": [], "web_url": "http://www.nytimes.com/2016/08/23/opinion/my-dream-double-bill.html", "slideshow_credits": null, "blog": [], "_id": "57bb495295d0e021d798201d", "headline": {"main": "My Dream Double Bill", "content_kicker": "Letter", "print_headline": "My Dream Double Bill", "kicker": "Letter"}}