{"news_desk": "OpEd", "print_page": null, "section_name": "false", "subsection_name": "false", "byline": {"original": "By THE EDITORS", "person": [], "organization": "THE EDITORS"}, "abstract": "Approximately 780,000 millennials are regular\u00a0Daily Show watchers.", "type_of_material": "Blog", "word_count": "267", "lead_paragraph": null, "pub_date": "2015-02-12T11:39:18Z", "document_type": "blogpost", "slideshow_credits": null, "headline": {"main": "Do Millennials Watch Jon Stewart?", "kicker": "Taking Note"}, "snippet": "Approximately 780,000 millennials are regular\u00a0Daily Show watchers.", "multimedia": [], "web_url": "http://takingnote.blogs.nytimes.com/2015/02/12/do-millennials-watch-jon-stewart/", "keywords": [{"rank": "1", "value": "Stewart, Jon", "name": "persons"}], "blog": [], "_id": "54dd3f2838f0d8448bfa3804", "source": "The New York Times"}