{"news_desk": "BookReview", "print_page": "6", "subsection_name": "Book Review", "section_name": "Books", "byline": [], "abstract": null, "type_of_material": "Letter", "word_count": "927", "keywords": [{"rank": "1", "value": "Books and Literature", "is_major": "N", "name": "subject"}], "lead_paragraph": "Readers respond to recent reviews of Richard Kluger\u2019s \u201cIndelible Ink,\u201d Richard Cohen\u2019s \u201cShe Made Me Laugh\u201d and more.", "pub_date": "2016-10-02T04:00:00+0000", "document_type": "article", "source": "The New York Times", "snippet": "Readers respond to recent reviews of Richard Kluger\u2019s \u201cIndelible Ink,\u201d Richard Cohen\u2019s \u201cShe Made Me Laugh\u201d and more....", "multimedia": [], "web_url": "http://www.nytimes.com/2016/10/02/books/review/letters-to-the-editor.html", "slideshow_credits": null, "blog": [], "_id": "57ee834295d0e021d79895d0", "headline": {"main": "Letters to the Editor", "print_headline": "Letters"}}