{"news_desk": "Business", "print_page": null, "section_name": "Business Day", "subsection_name": "Economy", "byline": {"original": "By REUTERS", "person": [], "organization": "REUTERS"}, "abstract": null, "type_of_material": "News", "word_count": "325", "lead_paragraph": "The Labor Department\u2019s index gained 0.4 percent as costs for gasoline and other goods increased.", "pub_date": "2015-07-16T00:00:00Z", "document_type": "article", "slideshow_credits": null, "headline": {"main": "Producer Prices Rose More Than Expected in June", "print_headline": "Prices Rise As Oil Costs Tick Upward"}, "snippet": "The Labor Department\u2019s index gained 0.4 percent as costs for gasoline and other goods increased.", "multimedia": [], "web_url": "http://www.nytimes.com/2015/07/16/business/economy/producer-prices-rose-more-than-expected-in-june.html", "keywords": [{"rank": "1", "is_major": "N", "value": "Producer Price Index", "name": "subject"}, {"rank": "2", "is_major": "N", "value": "Factories and Manufacturing", "name": "subject"}, {"rank": "3", "is_major": "N", "value": "Labor Department (US)", "name": "organizations"}, {"rank": "4", "is_major": "N", "value": "Federal Reserve System", "name": "organizations"}, {"rank": "5", "is_major": "N", "value": "Federal Reserve Bank of New York", "name": "organizations"}, {"rank": "6", "is_major": "N", "value": "United States Economy", "name": "subject"}, {"rank": "7", "is_major": "N", "value": "Inflation (Economics)", "name": "subject"}, {"rank": "8", "is_major": "N", "value": "Oil (Petroleum) and Gasoline", "name": "subject"}], "blog": [], "_id": "55a6acf738f0d8559844f539", "source": "The New York Times"}