{"news_desk": "Science", "print_page": "", "section_name": "Science", "subsection_name": "Space & Cosmos", "document_type": "article", "multimedia": [{"height": 126, "subtype": "wide", "legacy": {"widewidth": "190", "wide": "images/2015/01/17/world/BEAGLE-FLOATER/BEAGLE-FLOATER-thumbWide.jpg", "wideheight": "126"}, "type": "image", "width": 190, "url": "images/2015/01/17/world/BEAGLE-FLOATER/BEAGLE-FLOATER-thumbWide.jpg"}, {"height": 408, "subtype": "xlarge", "legacy": {"xlargewidth": "600", "xlargeheight": "408", "xlarge": "images/2015/01/17/world/BEAGLE-FLOATER/BEAGLE-FLOATER-articleLarge.jpg"}, "type": "image", "width": 600, "url": "images/2015/01/17/world/BEAGLE-FLOATER/BEAGLE-FLOATER-articleLarge.jpg"}, {"height": 75, "subtype": "thumbnail", "legacy": {"thumbnail": "images/2015/01/17/world/BEAGLE-FLOATER/BEAGLE-FLOATER-thumbStandard.jpg", "thumbnailwidth": "75", "thumbnailheight": "75"}, "type": "image", "width": 75, "url": "images/2015/01/17/world/BEAGLE-FLOATER/BEAGLE-FLOATER-thumbStandard.jpg"}], "abstract": null, "type_of_material": "News", "word_count": "740", "lead_paragraph": "A NASA probe spotted the intact spacecraft, which had not been seen or heard from since its landing attempt and was presumed destroyed.", "pub_date": "2015-01-17T00:00:00Z", "_id": "54b9485938f0d83735b5a5d0", "byline": {"contributor": "", "original": "By THE ASSOCIATED PRESS", "person": [], "organization": "THE ASSOCIATED PRESS"}, "source": "The New York Times", "snippet": "A NASA probe spotted the intact spacecraft, which had not been seen or heard from since its landing attempt and was presumed destroyed.", "web_url": "http://www.nytimes.com/2015/01/17/science/space/missing-lander-beagle-2-finally-located-on-mars.html", "slideshow_credits": null, "blog": [], "keywords": [{"rank": "1", "is_major": "N", "value": "Mars (Planet)", "name": "subject"}, {"rank": "2", "is_major": "N", "value": "Planets", "name": "subject"}, {"rank": "3", "is_major": "N", "value": "Space and Astronomy", "name": "subject"}, {"rank": "4", "is_major": "N", "value": "European Space Agency", "name": "organizations"}], "headline": {"main": "Mars Orbiter Spots Beagle 2, European Lander Missing Since 2003", "print_headline": "Missing lander Beagle-2 finally located on Mars, agency says"}}