{"news_desk": "World / Africa", "print_page": null, "subsection_name": "Africa", "section_name": "World", "byline": [], "abstract": null, "type_of_material": "Interactive Feature", "word_count": null, "keywords": [{"rank": "1", "value": "Gambia", "is_major": "N", "name": "glocations"}, {"rank": "2", "value": "Barrow, Adama (1965- )", "is_major": "N", "name": "persons"}, {"rank": "3", "value": "Jammeh, Yahya", "is_major": "N", "name": "persons"}, {"rank": "4", "value": "Immigration and Emigration", "is_major": "N", "name": "subject"}, {"rank": "5", "value": "Refugees and Displaced Persons", "is_major": "N", "name": "subject"}], "lead_paragraph": "As Gambia\u2019s political crisis captures the world\u2019s attention, we want to hear from its people. How do you think the new government will affect your life?", "pub_date": "2017-01-25T10:33:56+0000", "document_type": "multimedia", "source": "The New York Times", "snippet": "As Gambia\u2019s political crisis captures the world\u2019s attention, we want to hear from its people. How do you think the new government will affect your life?...", "multimedia": [{"height": 126, "subtype": "wide", "legacy": {"widewidth": "190", "wide": "images/2017/01/24/world/25gambia-callout/24GAmbia-Callout-thumbWide.jpg", "wideheight": "126"}, "type": "image", "width": 190, "url": "images/2017/01/24/world/25gambia-callout/24GAmbia-Callout-thumbWide.jpg"}, {"height": 400, "subtype": "xlarge", "legacy": {"xlargewidth": "600", "xlargeheight": "400", "xlarge": "images/2017/01/24/world/25gambia-callout/24GAmbia-Callout-articleLarge.jpg"}, "type": "image", "width": 600, "url": "images/2017/01/24/world/25gambia-callout/24GAmbia-Callout-articleLarge.jpg"}, {"height": 75, "subtype": "thumbnail", "legacy": {"thumbnailwidth": "75", "thumbnail": "images/2017/01/24/world/25gambia-callout/24GAmbia-Callout-thumbStandard.jpg", "thumbnailheight": "75"}, "type": "image", "width": 75, "url": "images/2017/01/24/world/25gambia-callout/24GAmbia-Callout-thumbStandard.jpg"}], "web_url": "http://www.nytimes.com/interactive/2017/01/25/world/africa/gambia-callout.html", "slideshow_credits": null, "blog": [], "_id": "58887f1a95d0e0392607ca74", "headline": {"main": "Are You From Gambia? We Want to Hear From You"}}