{"news_desk": "Sports", "print_page": "14", "section_name": "Sports", "subsection_name": "Soccer", "byline": {"contributor": "", "original": "By THE ASSOCIATED PRESS", "person": [], "organization": "THE ASSOCIATED PRESS"}, "abstract": "Brazil beats France, 3-1, in exhibition game in Paris.", "type_of_material": "Brief", "word_count": "42", "lead_paragraph": "Neymar scored his 43rd international goal and midfielder Willian set up two as Brazil beat France, 3-1, in an exhibition in Paris.", "pub_date": "2015-03-27T00:00:00Z", "document_type": "article", "slideshow_credits": null, "headline": {"main": "Brazil Defeats France in Exhibition", "content_kicker": "Sports Briefing | Soccer", "print_headline": "Brazil Defeats France in Exhibition"}, "snippet": "Neymar scored his 43rd international goal and midfielder Willian set up two as Brazil beat France, 3-1, in an exhibition in Paris.", "multimedia": [], "web_url": "http://www.nytimes.com/2015/03/27/sports/soccer/brazil-defeats-france-in-exhibition.html", "keywords": [{"rank": "1", "is_major": "Y", "value": "Soccer", "name": "subject"}, {"rank": "2", "is_major": "N", "value": "Brazil", "name": "glocations"}, {"rank": "3", "is_major": "N", "value": "France", "name": "glocations"}, {"rank": "4", "is_major": "N", "value": "Neymar", "name": "persons"}, {"rank": "5", "is_major": "N", "value": "Borges da Silva, Willian", "name": "persons"}], "blog": [], "_id": "5514d4c538f0d82942dd61d1", "source": "The New York Times"}